sc2maptool/__init__.py
sc2maptool/__main__.py
sc2maptool/__version__.py
sc2maptool/cli.py
sc2maptool/constants.py
sc2maptool/functions.py
sc2maptool/index.py
sc2maptool/mapRecord.py
sc2maptool/startup.py
sc2maptool/maps/Ladder/mode1v1/year2017/Season3/AbyssalReefLE.SC2Map
sc2maptool/maps/Ladder/mode1v1/year2017/Season3/AcolyteLE.SC2Map
sc2maptool/maps/Ladder/mode1v1/year2017/Season3/AscensiontoAiurLE.SC2Map
sc2maptool/maps/Ladder/mode1v1/year2017/Season3/FrostLE.SC2Map
sc2maptool/maps/Ladder/mode1v1/year2017/Season3/InterloperLE.SC2Map
sc2maptool/maps/Ladder/mode1v1/year2017/Season3/MechDepotLE.SC2Map
sc2maptool/maps/Ladder/mode1v1/year2017/Season3/OdysseyLE.SC2Map
sc2maptool/maps/Ladder/mode1v1/year2017/Season4/AbyssalReefLE.SC2Map
sc2maptool/maps/Ladder/mode1v1/year2017/Season4/AscensiontoAiurLE.SC2Map
sc2maptool/maps/Ladder/mode1v1/year2017/Season4/BattleOnTheBoardwalkLE.SC2Map
sc2maptool/maps/Ladder/mode1v1/year2017/Season4/BlackpinkLE.SC2Map
sc2maptool/maps/Ladder/mode1v1/year2017/Season4/CatalystLE.SC2Map
sc2maptool/maps/Ladder/mode1v1/year2017/Season4/NeonVioletSquareLE.SC2Map
sc2maptool/maps/Ladder/mode1v1/year2017/Season4/OdysseyLE.SC2Map
sc2maptool/maps/Ladder/mode1v1/year2018/Season1/AbiogenesisLE.SC2Map
sc2maptool/maps/Ladder/mode1v1/year2018/Season1/AcidPlantLE.SC2Map
sc2maptool/maps/Ladder/mode1v1/year2018/Season1/BackwaterLE.SC2Map
sc2maptool/maps/Ladder/mode1v1/year2018/Season1/BlackpinkLE.SC2Map
sc2maptool/maps/Ladder/mode1v1/year2018/Season1/CatalystLE.SC2Map
sc2maptool/maps/Ladder/mode1v1/year2018/Season1/EastwatchLE.SC2Map
sc2maptool/maps/Ladder/mode1v1/year2018/Season1/NeonVioletSquareLE.SC2Map
sc2maptool/maps/Ladder/mode1v1/year2018/Season2/16BitLE.SC2Map
sc2maptool/maps/Ladder/mode1v1/year2018/Season2/AcidPlantLE.SC2Map
sc2maptool/maps/Ladder/mode1v1/year2018/Season2/CatalystLE.SC2Map
sc2maptool/maps/Ladder/mode1v1/year2018/Season2/DarknessSanctuaryLE.SC2Map
sc2maptool-1.1.2.dist-info/METADATA
sc2maptool-1.1.2.dist-info/RECORD
sc2maptool-1.1.2.dist-info/WHEEL
sc2maptool-1.1.2.dist-info/entry_points.txt
sc2maptool-1.1.2.dist-info/top_level.txt
