Metadata-Version: 2.1
Name: sc2maptool
Version: 1.1.2
Summary: Manage Starcraft2 (SC2) maps for use by developers creating bots, AI agents or some other custom code project.
Home-page: https://github.com/ttinies/sc2gameMapRepo
Author: Versentiedge LLC
Author-email: help.fool@versentiedge.com
License: Apache License 2.0
Platform: UNKNOWN
Classifier: License :: OSI Approved :: Apache Software License
Classifier: Programming Language :: Python
Classifier: Programming Language :: Python :: 3
Classifier: Programming Language :: Python :: 3.6
Classifier: Programming Language :: Python :: Implementation :: CPython
Classifier: Programming Language :: Python :: Implementation :: PyPy
Classifier: Topic :: Games/Entertainment :: Real Time Strategy
Classifier: Topic :: Scientific/Engineering :: Artificial Intelligence
Requires-Python: >3.4
Requires-Dist: six
Requires-Dist: sc2common
Requires-Dist: sc2gameLobby
